apt/__init__.py
apt/aptll.py
aptll-2.2.6.dist-info/LICENSE
aptll-2.2.6.dist-info/METADATA
aptll-2.2.6.dist-info/WHEEL
aptll-2.2.6.dist-info/top_level.txt
aptll-2.2.6.dist-info/RECORD
